src/__init__.py
src/server.py
src/worker.py
adworld_render_worker-0.1.0.dist-info/WHEEL
adworld_render_worker-0.1.0.dist-info/METADATA
adworld_render_worker-0.1.0.dist-info/RECORD
