Metadata-Version: 2.1
Name: adworld-render-worker
Version: 0.1.0
Summary: The render worker for the adworld pipeline
License: BSD
Author: Ezra Goss
Author-email: ezragoss@gmail.com
Requires-Python: >=3.10,<4.0
Classifier: License :: Other/Proprietary License
Classifier: Programming Language :: Python :: 3
Classifier: Programming Language :: Python :: 3.10
Requires-Dist: fastapi (>=0.85.0,<0.86.0)
Requires-Dist: mypy (>=0.981,<0.982)
